prompt_engine/__init__.py
prompt_engine/chat_engine.py
prompt_engine/code_engine.py
prompt_engine/dynamic_prompt_engine.py
prompt_engine/interaction.py
prompt_engine/model_config.py
prompt_engine/prompt_engine.py
prompt_engine/utils/__init__.py
prompt_engine/utils/encoder.json
prompt_engine/utils/encoder.py
prompt_engine/utils/vocab.bpe
prompt_engine_py-0.0.2.dist-info/LICENSE
prompt_engine_py-0.0.2.dist-info/METADATA
prompt_engine_py-0.0.2.dist-info/WHEEL
prompt_engine_py-0.0.2.dist-info/top_level.txt
prompt_engine_py-0.0.2.dist-info/RECORD
