Metadata-Version: 2.1
Name: prompt-engine-py
Version: 0.0.2
Summary: This package is a utility library for creating and maintaining prompts for Large Language Models (LLMs).
Home-page: https://github.com/microsoft/prompt-engine-py
Author: Abhishek Masand
Author-email: amasand@microsoft.com
Project-URL: Bug Tracker, https://github.com/microsoft/prompt-engine-py/issues
Classifier: Programming Language :: Python :: 3
Classifier: License :: OSI Approved :: MIT License
Classifier: Operating System :: OS Independent
Requires-Python: >=3.6
License-File: LICENSE
